README.txt
setup.py
tkPickaColor/__init__.py
tkPickaColor/classpoint.py
tkPickaColor/colorservices.py
tkPickaColor/defaultvalues.py
tkPickaColor/gimppaletteparser.py
tkPickaColor/palettebuilder.py
tkPickaColor/test_enter.py
tkPickaColor/test_text_wid.py
tkPickaColor/textwidget.py
tkPickaColor/tkinterhelpers.py
tkPickaColor/tkpickacolor.py
tkPickaColor.egg-info/PKG-INFO
tkPickaColor.egg-info/SOURCES.txt
tkPickaColor.egg-info/dependency_links.txt
tkPickaColor.egg-info/top_level.txt