Metadata-Version: 1.0
Name: tkPickaColor
Version: 0.1
Summary: Tkinter dialog to provide Linux developers a more full featured color chooser
Home-page: UNKNOWN
Author: Steve Solomon
Author-email: codeduffer@gmail.com
License: UNKNOWN
Platform: UNKNOWN
Classifier: Development Status :: 3 - Alpha
Classifier: Intended Audience :: Developers
Classifier: License :: OSI Approved :: GNU General Public License (GPL)
Classifier: Natural Language :: English
Classifier: Operating System :: POSIX :: Linux
Classifier: Programming Language :: Python :: 2.6
Classifier: Topic :: Software Development :: Widget Sets
